oceandb_bigchaindb_driver/__init__.py
oceandb_bigchaindb_driver/instance.py
oceandb_bigchaindb_driver/plugin.py
oceandb_bigchaindb_driver-0.1.4.dist-info/LICENSE
oceandb_bigchaindb_driver-0.1.4.dist-info/METADATA
oceandb_bigchaindb_driver-0.1.4.dist-info/WHEEL
oceandb_bigchaindb_driver-0.1.4.dist-info/top_level.txt
oceandb_bigchaindb_driver-0.1.4.dist-info/RECORD
