Metadata-Version: 2.1
Name: oceandb-bigchaindb-driver
Version: 0.1.4
Summary: 🐳 Ocean DB BigchainDB driver (Python).
Home-page: https://github.com/oceanprotocol/oceandb-bigchaindb-driver
Author: leucothia
Author-email: devops@oceanprotocol.com
License: Apache Software License 2.0
Keywords: oceandb_bigchaindb_driver
Platform: UNKNOWN
Classifier: Development Status :: 2 - Pre-Alpha
Classifier: Intended Audience :: Developers
Classifier: License :: OSI Approved :: Apache Software License
Classifier: Natural Language :: English
Classifier: Programming Language :: Python :: 3.5
Classifier: Programming Language :: Python :: 3.6
Requires-Dist: oceandb-driver-interface
Requires-Dist: bigchaindb-driver
Requires-Dist: BigchainDB
